aldryn_blog/__init__.py
aldryn_blog/admin.py
aldryn_blog/cms_app.py
aldryn_blog/cms_plugins.py
aldryn_blog/cms_toolbar.py
aldryn_blog/conf.py
aldryn_blog/feeds.py
aldryn_blog/forms.py
aldryn_blog/models.py
aldryn_blog/search_indexes.py
aldryn_blog/tests.py
aldryn_blog/urls.py
aldryn_blog/utils.py
aldryn_blog/views.py
aldryn_blog/locale/de/LC_MESSAGES/django.mo
aldryn_blog/locale/de/LC_MESSAGES/django.po
aldryn_blog/locale/en/LC_MESSAGES/django.mo
aldryn_blog/locale/en/LC_MESSAGES/django.po
aldryn_blog/locale/fr/LC_MESSAGES/django.mo
aldryn_blog/locale/fr/LC_MESSAGES/django.po
aldryn_blog/locale/it/LC_MESSAGES/django.mo
aldryn_blog/locale/it/LC_MESSAGES/django.po
aldryn_blog/migrations/0001_initial.py
aldryn_blog/migrations/0002_auto__add_field_post_key_visual__add_field_post_lead_in.py
aldryn_blog/migrations/0003_auto__add_field_post_language.py
aldryn_blog/migrations/0004_date_to_datetime_step1.py
aldryn_blog/migrations/0005_date_to_datetime_step2.py
aldryn_blog/migrations/0006_date_to_datetime_step3.py
aldryn_blog/migrations/0007_normalize_plugin_language.py
aldryn_blog/migrations/0008_auto__add_authorentriesplugin.py
aldryn_blog/migrations/0009_auto__del_field_authorentriesplugin_author.py
aldryn_blog/migrations/0010_auto__del_field_authorentriesplugin_latest_entries.py
aldryn_blog/migrations/0011_rename__authorentriesplugin__to__authorsplugin.py
aldryn_blog/migrations/0012_rename__authorentriesplugin__to__authorsplugin.py
aldryn_blog/migrations/0013_auto__add_category__add_categorytranslation__add_unique_categorytransl.py
aldryn_blog/migrations/0013_auto__add_m2m_coauthor.py
aldryn_blog/migrations/0015_auto__add_field_post_app_data.py
aldryn_blog/migrations/__init__.py
aldryn_blog/sitemaps/__init__.py
aldryn_blog/sitemaps/sitemap.py
aldryn_blog/templates/admin/aldryn_blog/post/change_form.html
aldryn_blog/templates/aldryn_blog/author_list.html
aldryn_blog/templates/aldryn_blog/base.html
aldryn_blog-0.4.4.2.dist-info/DESCRIPTION.rst
aldryn_blog-0.4.4.2.dist-info/METADATA
aldryn_blog-0.4.4.2.dist-info/metadata.json
aldryn_blog-0.4.4.2.dist-info/RECORD
aldryn_blog-0.4.4.2.dist-info/top_level.txt
aldryn_blog-0.4.4.2.dist-info/WHEEL
