Metadata-Version: 2.0
Name: aldryn-blog
Version: 0.4.4.2
Summary: Adds blogging abilities to django CMS
Home-page: https://github.com/aldryn/aldryn-blog
Author: Divio AG
Author-email: info@divio.ch
License: LICENSE.txt
Platform: OS Independent
Classifier: Development Status :: 2 - Pre-Alpha
Classifier: Environment :: Web Environment
Classifier: Framework :: Django
Classifier: Intended Audience :: Developers
Classifier: License :: OSI Approved :: BSD License
Classifier: Operating System :: OS Independent
Classifier: Programming Language :: Python
Classifier: Topic :: Internet :: WWW/HTTP :: Dynamic Content
Classifier: Topic :: Software Development
Classifier: Topic :: Software Development :: Libraries :: Application Frameworks
Requires-Dist: django-taggit (<0.12)
Requires-Dist: django-filer
Requires-Dist: django-select2
Requires-Dist: djangocms-text-ckeditor
Requires-Dist: django-appconf
Requires-Dist: django-classy-tags
Requires-Dist: south (>=0.8)
Requires-Dist: aldryn-common
Requires-Dist: django-hvad
Requires-Dist: unidecode
Requires-Dist: django-appdata
